MANIFEST.in
setup.py
doc_generator/__init__.py
doc_generator/driver_table_gen.py
doc_generator/module_info.py
va_dashboard/__init__.py
va_dashboard/build.js
va_dashboard/src/app.js
va_dashboard/src/login.js
va_dashboard/src/network.js
va_dashboard/src/tabs/apps.js
va_dashboard/src/tabs/basic_components.js
va_dashboard/src/tabs/chart_panel.js
va_dashboard/src/tabs/home.js
va_dashboard/src/tabs/hosts.js
va_dashboard/src/tabs/main_components.js
va_dashboard/src/tabs/overview.js
va_dashboard/src/tabs/panel.js
va_dashboard/src/tabs/store.js
va_dashboard/src/tabs/subpanel.js
va_dashboard/src/tabs/triggers.js
va_dashboard/src/tabs/ts_status.js
va_dashboard/src/tabs/vpn.js
va_dashboard/src/tabs/vpn_logins.js
va_dashboard/static/bundle.js
va_dashboard/static/index.html
va_dashboard/static/jquery.min.js
va_dashboard/static/logo-splash.png
va_dashboard/static/logo.png
va_dashboard/static/sidebar.png
va_dashboard/static/css/bootstrap-theme.min.css
va_dashboard/static/css/bootstrap.min.css
va_dashboard/static/css/font-awesome.min.css
va_dashboard/static/css/style.css
va_dashboard/static/fonts/fontawesome-webfont.eot
va_dashboard/static/fonts/fontawesome-webfont.svg
va_dashboard/static/fonts/fontawesome-webfont.ttf
va_dashboard/static/fonts/fontawesome-webfont.woff
va_dashboard/static/fonts/glyphicons-halflings-regular.eot
va_dashboard/static/fonts/glyphicons-halflings-regular.svg
va_dashboard/static/fonts/glyphicons-halflings-regular.ttf
va_dashboard/static/fonts/glyphicons-halflings-regular.woff
va_master/__init__.py
va_master/__main__.py
va_master/cli.py
va_master/cli_environment.py
va_master/config.py
va_master/datastore.py
va_master/deploy_handler.py
va_master/server.py
va_master/tests.py
va_master/api/__init__.py
va_master/api/apps.py
va_master/api/handler.py
va_master/api/hosts.py
va_master/api/login.py
va_master/api/panels.py
va_master/api/status.py
va_master/api/triggers.py
va_master/api/url_handler.py
va_master/host_drivers/__init__.py
va_master/host_drivers/aws.py
vapourapps.egg-info/PKG-INFO
vapourapps.egg-info/SOURCES.txt
vapourapps.egg-info/dependency_links.txt
vapourapps.egg-info/entry_points.txt
vapourapps.egg-info/requires.txt
vapourapps.egg-info/top_level.txt