Metadata-Version: 1.0
Name: vapourapps
Version: 1.0.1
Summary: This package contains the master server of VapourApps, a DevOps tool for corporate apps.
Home-page: UNKNOWN
Author: VapourApps
Author-email: UNKNOWN
License: UNKNOWN
Keywords: vapourapps
Platform: UNKNOWN
